work_tool_mcp/__init__.py
work_tool_mcp/__main__.py
work_tool_mcp/exceptions.py
work_tool_mcp/server.py
work_tool_mcp/constants/__init__.py
work_tool_mcp/constants/fonts.py
work_tool_mcp/tools/__init__.py
work_tool_mcp/tools/excel_handler.py
work_tool_mcp/tools/pdf_handler.py
work_tool_mcp/tools/save_pdf_info.py
work_tool_mcp/tools/text_handler.py
work_tool_mcp-0.1.5.dist-info/METADATA
work_tool_mcp-0.1.5.dist-info/WHEEL
work_tool_mcp-0.1.5.dist-info/entry_points.txt
work_tool_mcp-0.1.5.dist-info/RECORD
